{
  "main": {
    "id": "b6235258a3cd3e53",
    "type": "split",
    "children": [
      {
        "id": "bae9baf7f0ad03d6",
        "type": "split",
        "children": [
          {
            "id": "54117a93bc86c027",
            "type": "tabs",
            "children": [
              {
                "id": "2c4727453e2c28ba",
                "type": "leaf",
                "state": {
                  "type": "markdown",
                  "state": {
                    "file": "Namaste React/React.md",
                    "mode": "source",
                    "source": false
                  },
                  "icon": "lucide-file",
                  "title": "React"
                }
              },
              {
                "id": "db49d8d4a45cf5df",
                "type": "leaf",
                "state": {
                  "type": "markdown",
                  "state": {
                    "file": "Namaste React/React.md",
                    "mode": "source",
                    "source": false
                  },
                  "icon": "lucide-file",
                  "title": "React"
                }
              },
              {
                "id": "8a6ff3c6175ae1ff",
                "type": "leaf",
                "state": {
                  "type": "markdown",
                  "state": {
                    "file": "Namaste React/What is React !.md",
                    "mode": "source",
                    "source": false
                  },
                  "icon": "lucide-file",
                  "title": "What is React !"
                }
              },
              {
                "id": "ccc17d648d9c21f9",
                "type": "leaf",
                "state": {
                  "type": "markdown",
                  "state": {
                    "file": "Namaste React/React.md",
                    "mode": "source",
                    "source": false
                  },
                  "icon": "lucide-file",
                  "title": "React"
                },
                "group": "4cfcac758c3061d6"
              },
              {
                "id": "13d9b169f177ff1d",
                "type": "leaf",
                "state": {
                  "type": "empty",
                  "state": {},
                  "icon": "lucide-file",
                  "title": "New tab"
                }
              }
            ],
            "currentTab": 3
          },
          {
            "id": "0367319e796795b0",
            "type": "tabs",
            "children": [
              {
                "id": "269ca72526dfb627",
                "type": "leaf",
                "pinned": true,
                "state": {
                  "type": "terminal:terminal",
                  "state": {
                    "terminal:terminal": {
                      "cwd": "C:\\Users\\user\\Documents\\Obsidian\\My Vault",
                      "focus": false,
                      "profile": {
                        "args": [],
                        "executable": "C:\\Windows\\System32\\cmd.exe",
                        "name": "",
                        "platforms": {
                          "win32": true
                        },
                        "pythonExecutable": "python3",
                        "restoreHistory": true,
                        "successExitCodes": [
                          "0",
                          "SIGINT",
                          "SIGTERM"
                        ],
                        "terminalOptions": {
                          "documentOverride": null
                        },
                        "type": "integrated",
                        "useWin32Conhost": true
                      },
                      "serial": {
                        "columns": 89,
                        "data": "\r\nC:\\Users\\user\\Documents\\Obsidian\\My Vault>git status\r\nOn branch notes-branch\r\nYour branch is up to date with 'origin/notes-branch'.\r\n\r\nChanges not staged for commit:\r\n  (use \"git add <file>...\" to update what will be committed)\r\n  (use \"git restore <file>...\" to discard changes in working directory)\r\n\u001b[8C\u001b[31mmodified:   .obsidian/workspace.json\r\n\r\n\u001b[0mno changes added to commit (use \"git add\" and/or \"git commit -a\")\r\n\r\nC:\\Users\\user\\Documents\\Obsidian\\My Vault>cat .obsidian/workspace.json\r\n{\r\n  \"main\": {\r\n    \"id\": \"b6235258a3cd3e53\",\r\n    \"type\": \"split\",\r\n    \"children\": [\r\n      {\r\n        \"id\": \"bae9baf7f0ad03d6\",\r\n        \"type\": \"split\",\r\n        \"children\": [\r\n          {\r\n            \"id\": \"54117a93bc86c027\",\r\n            \"type\": \"tabs\",\r\n            \"children\": [\r\n              {\r\n                \"id\": \"2c4727453e2c28ba\",\r\n                \"type\": \"leaf\",\r\n                \"state\": {\r\n                  \"type\": \"markdown\",\r\n                  \"state\": {\r\n                    \"file\": \"Namaste React/React.md\",\r\n                    \"mode\": \"source\",\r\n                    \"source\": false\r\n                  },\r\n                  \"icon\": \"lucide-file\",\r\n                  \"title\": \"React\"\r\n                }\r\n              },\r\n              {\r\n                \"id\": \"db49d8d4a45cf5df\",\r\n                \"type\": \"leaf\",\r\n                \"state\": {\r\n                  \"type\": \"markdown\",\r\n                  \"state\": {\r\n                    \"file\": \"Namaste React/React.md\",\r\n                    \"mode\": \"source\",\r\n                    \"source\": false\r\n                  },\r\n\u001b[16C  \"icon\": \"lucide-file\",\r\n                  \"title\": \"React\"\r\n                }\r\n              },\r\n              {\r\n                \"id\": \"8a6ff3c6175ae1ff\",\r\n                \"type\": \"leaf\",\r\n                \"state\": {\r\n                  \"type\": \"markdown\",\r\n                  \"state\": {\r\n                    \"file\": \"Namaste React/What is React !.md\",\r\n                    \"mode\": \"source\",\r\n                    \"source\": false\r\n                  },\r\n                  \"icon\": \"lucide-file\",\r\n                  \"title\": \"What is React !\"\r\n                }\r\n              },\r\n              {\r\n                \"id\": \"ccc17d648d9c21f9\",\r\n                \"type\": \"leaf\",\r\n                \"state\": {\r\n                  \"type\": \"markdown\",\r\n                  \"state\": {\r\n                    \"file\": \"Namaste React/React.md\",\r\n                    \"mode\": \"source\",\r\n                    \"source\": false\r\n                  },\r\n                  \"icon\": \"lucide-file\",\r\n                  \"title\": \"React\"\r\n                },\r\n                \"group\": \"4cfcac758c3061d6\"\r\n              },\r\n              {\r\n                \"id\": \"13d9b169f177ff1d\",\r\n                \"type\": \"leaf\",\r\n                \"state\": {\r\n                  \"type\": \"empty\",\r\n                  \"state\": {},\r\n                  \"icon\": \"lucide-file\",\r\n                  \"title\": \"New tab\"\r\n                }\r\n              }\r\n            ],\r\n            \"currentTab\": 3\r\n          },\r\n          {\r\n            \"id\": \"0367319e796795b0\",\r\n            \"type\": \"tabs\",\r\n            \"children\": [\r\n              {\r\n                \"id\": \"269ca72526dfb627\",\r\n                \"type\": \"leaf\",\r\n                \"pinned\": true,\r\n                \"state\": {\r\n                  \"type\": \"terminal:terminal\",\r\n                  \"state\": {\r\n                    \"terminal:terminal\": {\r\n                      \"cwd\": \"C:\\\\Users\\\\user\\\\Documents\\\\Obsidian\\\\My Vault\",\r\n                      \"focus\": false,\r\n                      \"profile\": {\r\n                        \"args\": [],\r\n                        \"executable\": \"C:\\\\Windows\\\\System32\\\\cmd.exe\",\r\n                        \"name\": \"\",\r\n                        \"platforms\": {\r\n                          \"win32\": true\r\n                        },\r\n                        \"pythonExecutable\": \"python3\",\r\n\u001b[20C    \"restoreHistory\": true,\r\n                        \"successExitCodes\": [\r\n                          \"0\",\r\n                          \"SIGINT\",\r\n                          \"SIGTERM\"\r\n                        ],\r\n                        \"terminalOptions\": {\r\n                          \"documentOverride\": null\r\n                        },\r\n                        \"type\": \"integrated\",\r\n                        \"useWin32Conhost\": true\r\n                      },\r\n                      \"serial\": {\r\n                        \"columns\": 89,\r\n                        \"data\": \"\\r\\nC:\\\\Users\\\\user\\\\Documents\\\\Obsidian\\\\My Vault>git status\\r\\nOn branch notes-branch\r\n\u001b[88Ch\\r\\nYour branch is up to date with 'origin/notes-branch'.\\r\\n\\r\\nChanges not staged for commit:\\r\\n  (use \\\"git add <fil\r\n\u001b[88Cle>...\\\" to update what will be committed)\\r\\n  (use \\\"git restore <file>...\\\" to discard changes in working directory)\\r\r\n\u001b[88Cr\\n\\u001b[8C\\u001b[31mmodified:   .obsidian/workspace.json\\r\\n\\r\\n\\u001b[0mno changes added to commit (use \\\"git a       \u001b[57Cdd\\\" an\r\n\u001b[88Cnd/or \\\"git commit -a\\\")\\r\\n\\r\\nC:\\\\Users\\\\user\\\\Documents\\\\Obsidian\\\\My Vault>cat .obsidian/workspace.\",\r\n                        \"rows\": 24\r\n                      }\r\n                    }\r\n                  },\r\n                  \"pinned\": true,\r\n                  \"icon\": \"terminal\",\r\n                  \"title\": \"Terminal: C:\\\\Windows\\\\System32\\\\conhost.exe\"\r\n                }\r\n              }\r\n            ]\r\n          }\r\n        ],\r\n        \"direction\": \"horizontal\"\r\n      },\r\n      {\r\n        \"id\": \"ab7f39c2b45416c2\",\r\n        \"type\": \"tabs\",\r\n        \"children\": [\r\n          {\r\n            \"id\": \"39a1f2d0f0d102b0\",\r\n            \"type\": \"leaf\",\r\n            \"state\": {\r\n              \"type\": \"localgraph\",\r\n              \"state\": {\r\n                \"file\": \"Namaste React/React.md\",\r\n                \"options\": {\r\n                  \"collapse-filter\": true,\r\n                  \"search\": \"\",\r\n                  \"localJumps\": 1,\r\n                  \"localBacklinks\": true,\r\n                  \"localForelinks\": true,\r\n                  \"localInterlinks\": false,\r\n                  \"showTags\": false,\r\n                  \"showAttachments\": false,\r\n                  \"hideUnresolved\": false,\r\n                  \"collapse-color-groups\": true,\r\n                  \"colorGroups\": [],\r\n                  \"collapse-display\": false,\r\n                  \"showArrow\": true,\r\n                  \"textFadeMultiplier\": 0,\r\n                  \"nodeSizeMultiplier\": 1,\r\n                  \"lineSizeMultiplier\": 1,\r\n                  \"collapse-forces\": true,\r\n                  \"centerStrength\": 0.518713248970312,\r\n                  \"repelStrength\": 10,\r\n                  \"linkStrength\": 1,\r\n                  \"linkDistance\": 250,\r\n                  \"scale\": 1,\r\n                  \"close\": true\r\n                }\r\n              },\r\n              \"icon\": \"lucide-git-fork\",\r\n              \"title\": \"Graph of React\"\r\n            },\r\n            \"group\": \"4cfcac758c3061d6\"\r\n          }\r\n        ]\r\n      }\r\n    ],\r\n    \"direction\": \"vertical\"\r\n  },\r\n  \"left\": {\r\n    \"id\": \"fe7a3b4935681828\",\r\n    \"type\": \"split\",\r\n    \"children\": [\r\n      {\r\n        \"id\": \"9a1667e9e53bef7c\",\r\n        \"type\": \"tabs\",\r\n        \"children\": [\r\n          {\r\n            \"id\": \"8a1216ed5cbfabf6\",\r\n            \"type\": \"leaf\",\r\n            \"state\": {\r\n              \"type\": \"file-explorer\",\r\n              \"state\": {\r\n                \"sortOrder\": \"alphabetical\"\r\n              },\r\n              \"icon\": \"lucide-folder-closed\",\r\n              \"title\": \"Files\"\r\n            }\r\n          },\r\n          {\r\n            \"id\": \"a4776180c592c204\",\r\n            \"type\": \"leaf\",\r\n            \"state\": {\r\n              \"type\": \"search\",\r\n              \"state\": {\r\n                \"query\": \"\",\r\n                \"matchingCase\": false,\r\n                \"explainSearch\": false,\r\n                \"collapseAll\": false,\r\n                \"extraContext\": false,\r\n                \"sortOrder\": \"alphabetical\"\r\n              },\r\n              \"icon\": \"lucide-search\",\r\n              \"title\": \"Search\"\r\n            }\r\n          },\r\n          {\r\n            \"id\": \"1f6dcc60afb4d672\",\r\n            \"type\": \"leaf\",\r\n            \"state\": {\r\n              \"type\": \"bookmarks\",\r\n\u001b[8C      \"state\": {},\r\n              \"icon\": \"lucide-bookmark\",\r\n              \"title\": \"Bookmarks\"\r\n            }\r\n          }\r\n        ]\r\n      }\r\n    ],\r\n    \"direction\": \"horizontal\",\r\n    \"width\": 200\r\n  },\r\n  \"right\": {\r\n    \"id\": \"61e9a01d25bf5491\",\r\n    \"type\": \"split\",\r\n    \"children\": [\r\n      {\r\n        \"id\": \"7423fe1b9cf58b83\",\r\n        \"type\": \"tabs\",\r\n        \"children\": [\r\n          {\r\n            \"id\": \"df1ff1041c24089e\",\r\n            \"type\": \"leaf\",\r\n            \"state\": {\r\n              \"type\": \"backlink\",\r\n              \"state\": {\r\n                \"collapseAll\": false,\r\n                \"extraContext\": false,\r\n                \"sortOrder\": \"alphabetical\",\r\n                \"showSearch\": false,\r\n                \"searchQuery\": \"\",\r\n                \"backlinkCollapsed\": false,\r\n                \"unlinkedCollapsed\": false\r\n              },\r\n              \"icon\": \"links-coming-in\",\r\n              \"title\": \"Backlinks\"\r\n            }\r\n          },\r\n          {\r\n            \"id\": \"bd2b772f971f1af3\",\r\n            \"type\": \"leaf\",\r\n            \"state\": {\r\n              \"type\": \"outgoing-link\",\r\n              \"state\": {\r\n                \"linksCollapsed\": false,\r\n                \"unlinkedCollapsed\": false\r\n              },\r\n              \"icon\": \"links-going-out\",\r\n              \"title\": \"Outgoing links\"\r\n            }\r\n          },\r\n          {\r\n            \"id\": \"d02b174327539d91\",\r\n            \"type\": \"leaf\",\r\n            \"state\": {\r\n              \"type\": \"tag\",\r\n              \"state\": {\r\n                \"sortOrder\": \"frequency\",\r\n                \"useHierarchy\": true\r\n              },\r\n              \"icon\": \"lucide-tags\",\r\n              \"title\": \"Tags\"\r\n            }\r\n          },\r\n          {\r\n            \"id\": \"a3988edc557249b4\",\r\n            \"type\": \"leaf\",\r\n            \"state\": {\r\n              \"type\": \"outline\",\r\n              \"state\": {},\r\n              \"icon\": \"lucide-list\",\r\n              \"title\": \"Outline\"\r\n            }\r\n          },\r\n          {\r\n            \"id\": \"c0cacb560edd5c87\",\r\n            \"type\": \"leaf\",\r\n            \"state\": {\r\n              \"type\": \"calendar\",\r\n\u001b[2C            \"state\": {},\r\n              \"icon\": \"calendar-with-checkmark\",\r\n              \"title\": \"Calendar\"\r\n            }\r\n          },\r\n          {\r\n            \"id\": \"50029051ddc0a71e\",\r\n            \"type\": \"leaf\",\r\n            \"state\": {\r\n              \"type\": \"git-view\",\r\n              \"state\": {},\r\n              \"icon\": \"git-pull-request\",\r\n              \"title\": \"Source Control\"\r\n            }\r\n          }\r\n        ],\r\n        \"currentTab\": 5\r\n      }\r\n    ],\r\n    \"direction\": \"horizontal\",\r\n    \"width\": 200,\r\n    \"collapsed\": true\r\n  },\r\n  \"left-ribbon\": {\r\n    \"hiddenItems\": {\r\n      \"switcher:Open quick switcher\": false,\r\n      \"graph:Open graph view\": false,\r\n      \"canvas:Create new canvas\": false,\r\n      \"templates:Insert template\": false,\r\n      \"command-palette:Open command palette\": false,\r\n      \"daily-notes:Open today's daily note\": false,\r\n      \"obsidian-hypothesis-plugin:Sync your hypothesis highlights\": false,\r\n      \"obsidian-git:Open Git source control\": false,\r\n      \"terminal:Open terminal\": false\r\n    }\r\n  },\r\n  \"active\": \"269ca72526dfb627\",\r\n  \"lastOpenFiles\": [\r\n    \"Namaste React/React.md\",\r\n    \"Namaste React/What is React !.md\",\r\n    \"Namaste React/Difference Between Library and Framework.md\",\r\n    \"Daily/28-Nov-2024 Thursday.md\",\r\n    \"attachments/Pasted image 20241128010843.png\",\r\n    \"Untitled.canvas\",\r\n    \"Untitled.md\",\r\n    \"How to Start Coding A Beginners Guide to Learning Programming - GeeksforGeeks.md\",\r\n    \"Avoid These 5 Mistakes as a Web Developer.md\",\r\n    \"10 essential VS Code tips & tricks for greater productivity.md\",\r\n    \"Hypothesis.md\",\r\n    \"attachments\",\r\n    \"React/new.md\",\r\n    \"React/styling_new.md\",\r\n    \"React/styling.md\",\r\n    \"React/tailwind.md\",\r\n    \"React/Virtual DOM.md\",\r\n    \"React/DOM.md\",\r\n    \"React/Untitled.canvas\",\r\n    \"asdasd.md\",\r\n    \"React/ReactLearning.md\",\r\n    \"lalla.md\",\r\n    \"newnote.md\",\r\n    \"React/Grid.md\",\r\n    \"a;iog.md\",\r\n    \"React/flexBox.md\",\r\n    \"alignauto.md\",\r\n    \"React/[flexBox.md\",\r\n    \"ReactJs.md\",\r\n    \"Namaste React\",\r\n    \"Untitled 1.canvas\",\r\n    \"Welcome.md\",\r\n    \"Daily\",\r\n    \"daily\"\r\n  ]\r\n}\r\nC:\\Users\\user\\Documents\\Obsidian\\My Vault>git diff\r\n\u001b[1mdiff --git a/My Vault/.obsidian/workspace.json b/My Vault/.obsidian/workspace.json\r\nindex a33e37c..69a1fc5 100644\r\n--- a/My Vault/.obsidian/workspace.json\r\n+++ b/My Vault/.obsidian/workspace.json\r\n\u001b[36;22m@@ -4,7 +4,7 @@\r\n\u001b[0m     \"type\": \"split\",\r\n     \"children\": [\r\n       {\r\n\u001b[31m-        \"id\": \"b6cd2f3a3d98418e\",\r\n\u001b[32m+        \"id\": \"bae9baf7f0ad03d6\",\r\n\u001b[0m         \"type\": \"split\",\r\n         \"children\": [\r\n           {\r\n\u001b[36m@@ -82,11 +82,11 @@\r\n\u001b[0m             \"currentTab\": 3\r\n           },\r\n           {\r\n\u001b[31m-            \"id\": \"788659b58ed62936\",\r\n\u001b[32m+            \"id\": \"0367319e796795b0\",\r\n\u001b[0m             \"type\": \"tabs\",\r\n             \"children\": [\r\n               {\r\n\u001b[31m-                \"id\": \"d97d07872c7887cf\",\r\n\u001b[32m+                \"id\": \"269ca72526dfb627\",\r\n\u001b[0m                 \"type\": \"leaf\",\r\n                 \"pinned\": true,\r\n                 \"state\": {\r\n\u001b[36m@@ -96,7 +96,13 @@\r\n\u001b[0m                       \"cwd\": \"C:\\\\Users\\\\user\\\\Documents\\\\Obsidian\\\\My Vault\",\r\n\r\nC:\\Users\\user\\Documents\\Obsidian\\My Vault>clear\r\n'clear' is not recognized as an internal or external command,\r\noperable program or batch file.\r\n\r\nC:\\Users\\user\\Documents\\Obsidian\\My Vault>git add ",
                        "rows": 24
                      }
                    }
                  },
                  "pinned": true,
                  "icon": "terminal",
                  "title": "Terminal: C:\\Windows\\System32\\conhost.exe"
                }
              }
            ]
          }
        ],
        "direction": "horizontal"
      },
      {
        "id": "ab7f39c2b45416c2",
        "type": "tabs",
        "children": [
          {
            "id": "39a1f2d0f0d102b0",
            "type": "leaf",
            "state": {
              "type": "localgraph",
              "state": {
                "file": "Namaste React/React.md",
                "options": {
                  "collapse-filter": true,
                  "search": "",
                  "localJumps": 1,
                  "localBacklinks": true,
                  "localForelinks": true,
                  "localInterlinks": false,
                  "showTags": false,
                  "showAttachments": false,
                  "hideUnresolved": false,
                  "collapse-color-groups": true,
                  "colorGroups": [],
                  "collapse-display": false,
                  "showArrow": true,
                  "textFadeMultiplier": 0,
                  "nodeSizeMultiplier": 1,
                  "lineSizeMultiplier": 1,
                  "collapse-forces": true,
                  "centerStrength": 0.518713248970312,
                  "repelStrength": 10,
                  "linkStrength": 1,
                  "linkDistance": 250,
                  "scale": 1,
                  "close": true
                }
              },
              "icon": "lucide-git-fork",
              "title": "Graph of React"
            },
            "group": "4cfcac758c3061d6"
          }
        ]
      }
    ],
    "direction": "vertical"
  },
  "left": {
    "id": "fe7a3b4935681828",
    "type": "split",
    "children": [
      {
        "id": "9a1667e9e53bef7c",
        "type": "tabs",
        "children": [
          {
            "id": "8a1216ed5cbfabf6",
            "type": "leaf",
            "state": {
              "type": "file-explorer",
              "state": {
                "sortOrder": "alphabetical"
              },
              "icon": "lucide-folder-closed",
              "title": "Files"
            }
          },
          {
            "id": "a4776180c592c204",
            "type": "leaf",
            "state": {
              "type": "search",
              "state": {
                "query": "",
                "matchingCase": false,
                "explainSearch": false,
                "collapseAll": false,
                "extraContext": false,
                "sortOrder": "alphabetical"
              },
              "icon": "lucide-search",
              "title": "Search"
            }
          },
          {
            "id": "1f6dcc60afb4d672",
            "type": "leaf",
            "state": {
              "type": "bookmarks",
              "state": {},
              "icon": "lucide-bookmark",
              "title": "Bookmarks"
            }
          }
        ]
      }
    ],
    "direction": "horizontal",
    "width": 200
  },
  "right": {
    "id": "61e9a01d25bf5491",
    "type": "split",
    "children": [
      {
        "id": "7423fe1b9cf58b83",
        "type": "tabs",
        "children": [
          {
            "id": "df1ff1041c24089e",
            "type": "leaf",
            "state": {
              "type": "backlink",
              "state": {
                "collapseAll": false,
                "extraContext": false,
                "sortOrder": "alphabetical",
                "showSearch": false,
                "searchQuery": "",
                "backlinkCollapsed": false,
                "unlinkedCollapsed": false
              },
              "icon": "links-coming-in",
              "title": "Backlinks"
            }
          },
          {
            "id": "bd2b772f971f1af3",
            "type": "leaf",
            "state": {
              "type": "outgoing-link",
              "state": {
                "linksCollapsed": false,
                "unlinkedCollapsed": false
              },
              "icon": "links-going-out",
              "title": "Outgoing links"
            }
          },
          {
            "id": "d02b174327539d91",
            "type": "leaf",
            "state": {
              "type": "tag",
              "state": {
                "sortOrder": "frequency",
                "useHierarchy": true
              },
              "icon": "lucide-tags",
              "title": "Tags"
            }
          },
          {
            "id": "a3988edc557249b4",
            "type": "leaf",
            "state": {
              "type": "outline",
              "state": {},
              "icon": "lucide-list",
              "title": "Outline"
            }
          },
          {
            "id": "c0cacb560edd5c87",
            "type": "leaf",
            "state": {
              "type": "calendar",
              "state": {},
              "icon": "calendar-with-checkmark",
              "title": "Calendar"
            }
          },
          {
            "id": "50029051ddc0a71e",
            "type": "leaf",
            "state": {
              "type": "git-view",
              "state": {},
              "icon": "git-pull-request",
              "title": "Source Control"
            }
          }
        ],
        "currentTab": 5
      }
    ],
    "direction": "horizontal",
    "width": 200,
    "collapsed": true
  },
  "left-ribbon": {
    "hiddenItems": {
      "switcher:Open quick switcher": false,
      "graph:Open graph view": false,
      "canvas:Create new canvas": false,
      "templates:Insert template": false,
      "command-palette:Open command palette": false,
      "daily-notes:Open today's daily note": false,
      "obsidian-hypothesis-plugin:Sync your hypothesis highlights": false,
      "obsidian-git:Open Git source control": false,
      "terminal:Open terminal": false
    }
  },
  "active": "269ca72526dfb627",
  "lastOpenFiles": [
    "Namaste React/React.md",
    "Namaste React/What is React !.md",
    "Namaste React/Difference Between Library and Framework.md",
    "Daily/28-Nov-2024 Thursday.md",
    "attachments/Pasted image 20241128010843.png",
    "Untitled.canvas",
    "Untitled.md",
    "How to Start Coding A Beginners Guide to Learning Programming - GeeksforGeeks.md",
    "Avoid These 5 Mistakes as a Web Developer.md",
    "10 essential VS Code tips & tricks for greater productivity.md",
    "Hypothesis.md",
    "attachments",
    "React/new.md",
    "React/styling_new.md",
    "React/styling.md",
    "React/tailwind.md",
    "React/Virtual DOM.md",
    "React/DOM.md",
    "React/Untitled.canvas",
    "asdasd.md",
    "React/ReactLearning.md",
    "lalla.md",
    "newnote.md",
    "React/Grid.md",
    "a;iog.md",
    "React/flexBox.md",
    "alignauto.md",
    "React/[flexBox.md",
    "ReactJs.md",
    "Namaste React",
    "Untitled 1.canvas",
    "Welcome.md",
    "Daily",
    "daily"
  ]
}